{
    "1": {
        "title": "Counting Sheep",
        "hover": "On the bright side, I'm a survivor of over 9,000 sheep."
    },
    "2": {
        "title": "Hipster Deer",
        "hover": "No one understands just how profound my way of listening to music is."
    },
    "3": {
        "title": "Falling",
        "hover": "10/10, would fall again."
    },
    "4": {
        "title": "Candysaurus",
        "hover": "Even at 18, I'm not too old to dream..."
    },
    "5": {
        "title": "Caterpillars",
        "hover": "If I could categorize this catastrophe, I'd call it quite cataclysmic..."
    },
    "6": {
        "title": "Sunset",
        "hover": "I never know how to respond to compliments."
    },
    "7": {
        "title": "Learning",
        "hover": "7-panel comic"
    },
    "8": {
        "title": "Balloon",
        "hover": "Ahh well, I heard those clouds were bullies anyways."
    },
    "9": {
        "title": "Aim for the Moon",
        "hover": "It's pretty lonely on the moon anyways I guess."
    },
    "10": {
        "title": "Free floating",
        "hover": "Just going with the flow~"
    },
    "11": {
        "title": "Fred",
        "hover": "Ahh, Fred, you're always so happy, and I don't know how you do it."
    },
    "12": {
        "title": "The Sun Smiled",
        "hover": "And then the sun laughed."
    },
    "13": {
        "title": "All of My Friends",
        "hover": "We are the 99.9% of bacteria your hand sanitizer killed."
    },
    "14": {
        "title": "Character",
        "hover": "Only my cat can judge me."
    },
    "15": {
        "title": "Transcendence",
        "hover": "I am certain that every great philosopher who has ever lived also pooped."
    },
    "16": {
        "title": "Rapunzel",
        "hover": "I may not be a damsel in distress, but I hope you'd be noble enough to shave me anyways."
    },
    "17": {
        "title": "Lovebirds",
        "hover": "There are plenty of fish in the sea, but none of them can fly."
    },
    "18": {
        "title": "All My Wildest Dreams",
        "hover": "They say happiness is all about the feeling of being in control of your life... I hope you've mastered lucid dreaming!"
    },
    "19": {
        "title": "Imagination",
        "hover": "Shush that logic; yes, I learned to eat by imagination too... three times a day."
    },
    "20": {
        "title": "Better",
        "hover": "I'm also the most humble person here by far."
    },
    "21": {
        "title": "Cancer",
        "hover": "It's ironic what disease she spent her life researching..."
    },
    "22": {
        "title": "Winter",
        "hover": "And you're really hot, too."
    },
    "23": {
        "title": "The Pie",
        "hover": "Now those kids of mine better not be eating my apples."
    },
    "24": {
        "title": "Squirrel",
        "hover": "Call me nutty, but I've been trying to cashew fur tree years."
    },
    "25": {
        "title": "Walking Towards You",
        "hover": "And we shall be united for all eternity."
    },
    "26": {
        "title": "The Clouds",
        "hover": "This place feels strangely familiar to me."
    },
    "27": {
        "title": "The Bunny Who Hated Carrots",
        "hover": "I bet you're the kind of racist who thinks mice like cheese."
    },
    "28": {
        "title": "True Wonder",
        "hover": "\"The most beautiful experience we can have is the mysterious. It is the fundamental emotion which stands at the cradle of true art and true science. Whoever does not know it and can no longer wonder, no longer marvel, is as good as dead, and his eyes are dimmed.\" -- Albert Einstein"
    },
    "29": {
        "title": "Fetch",
        "hover": "Woof."
    },
    "30": {
        "title": "Wishing on a Star",
        "hover": "\"I want my kids to grow feathers and fly.\""
    },
    "31": {
        "title": "Hourglass",
        "hover": "+====+\r\n|(::)|\r\n| )( |\r\n|(..)|\r\n+====+"
    },
    "32": {
        "title": "Monotony",
        "hover": "Some things never change."
    },
    "33": {
        "title": "Hand Turkeys",
        "hover": "Happy Thanksgiving!"
    }
}